{"caseId":0,"data":{"LMB_CODE":"0000","TEST_CODE":"11052","SEX":"F","AGE_YEAR":"6","AGE_MONTH":"70","AGE_DAY":"2141","HOSPITAL_CODE":"31526","Default(Group_R)":"N","Default(Group_W)":"Y","Default(Group_P)":"Y","02_Size":"Normocytic","02_Size_NUM":"0","03_Chromicity":"Normochromic","03_Chromicity_NUM":"0","04_Anisocytosis":"Negative","04_Anisocytosis_NUM":"0","05_Poikilocytosis":"Negative","05_Poikilocytosis_NUM":"0","07_burr cell":"Negative","07_burr cell_NUM":"0","08_target cell":"Negative","08_target cell_NUM":"0","09_spherocyte":"Negative","09_spherocyte_NUM":"0","10_schistocyte":"Negative","10_schistocyte_NUM":"0","11_Dimorphism":"Negative","11_Dimorphism_NUM":"0","13_Polychromasia":"Negative","13_Polychromasia_NUM":"0","14_Basophilic stippling":"Negative","14_Basophilic stippling_NUM":"0","15_Howell-Jolly body":"Negative","15_Howell-Jolly body_NUM":"0","16_Tear drop cell":"Negative","16_Tear drop cell_NUM":"0","17_Nucleated RBC":"0","17_Nucleated RBC_NUM":"0","21_Number":"Normal","21_Number_NUM":"0","22_Maturation":"Normal","22_Maturation_NUM":"0","23_Neutro-toxic changes":"Negative","23_Neutro-toxic changes_NUM":"0","24_Neutro-Dohle body":"Negative","24_Neutro-Dohle body_NUM":"0","29_Number":"Normal","29_Number_NUM":"0","30_Size":"Normal","30_Size_NUM":"0","31_Clumping":"Negative","31_Clumping_NUM":"0","18_Hemoglobin":"Anemia","18_Hemoglobin_NUM":"0","19_RBC Agglutination":"Negative","19_RBC Agglutination_NUM":"0","41_Stomatocyte":"Negative","41_Stomatocyte_NUM":"0","42_Acanthocyte":"Negative","42_Acanthocyte_NUM":"0","43_Malaria":"Negative","43_Malaria_NUM":"0","44_RBC others":"Negative","44_RBC others_NUM":"0","51_Neutrophil":"Normal","51_Neutrophil_NUM":"0","53_Lymphocyte":"Normal","53_Lymphocyte_NUM":"0","55_Monocyte":"Normal","55_Monocyte_NUM":"0","56_Eosinophil":"Normal","56_Eosinophil_NUM":"0","57_Basophil":"Normal","57_Basophil_NUM":"0","61_Atypical lymphocyte":"Negative","61_Atypical lymphocyte_NUM":"0","62_Abnormal lymphocyte":"Negative","62_Abnormal lymphocyte_NUM":"0","63_Blast":"Negative","63_Blast_NUM":"0","64_Abnormal cells":"Negative","64_Abnormal cells_NUM":"0","65_WBC Others":"Negative","65_WBC Others_NUM":"0","71_PLT Others":"Negative","71_PLT Others_NUM":"0","91_Cell degeneration":"Negative","91_Cell degeneration_NUM":"0","92_Partial clot":"Negative","92_Partial clot_NUM":"0"}}